cornflakes/__init__.py
cornflakes/__main__.py
cornflakes/builder/__init__.py
cornflakes/builder/_generate_config_group_module.py
cornflakes/builder/_generate_config_module.py
cornflakes/builder/_generate_enum_module.py
cornflakes/cli/__init__.py
cornflakes/cli/bump.py
cornflakes/cli/entrypoint.py
cornflakes/cli/update.py
cornflakes/common/__init__.py
cornflakes/common/_check_type.py
cornflakes/common/_datetime_ms.py
cornflakes/common/_default_ca_path.py
cornflakes/common/_extract_var_names.py
cornflakes/common/_get_method_definition.py
cornflakes/common/_get_method_type_hint.py
cornflakes/common/_has_return_statement.py
cornflakes/common/_patch_module.py
cornflakes/common/_recursive_update.py
cornflakes/common/_type_to_str.py
cornflakes/common/_unquoted_string.py
cornflakes/decorator/__init__.py
cornflakes/decorator/_funcat.py
cornflakes/decorator/_indexer.py
cornflakes/decorator/_wrap_kwargs.py
cornflakes/decorator/_wrap_partial.py
cornflakes/decorator/click/__init__.py
cornflakes/decorator/click/_click_cli.py
cornflakes/decorator/click/_command.py
cornflakes/decorator/click/_fill_option_groups.py
cornflakes/decorator/click/_group.py
cornflakes/decorator/click/_patch_click.py
cornflakes/decorator/click/commands/__init__.py
cornflakes/decorator/click/commands/_bg_status.py
cornflakes/decorator/click/helper/__init__.py
cornflakes/decorator/click/helper/_click_param_type_parser.py
cornflakes/decorator/click/helper/_get_command_name.py
cornflakes/decorator/click/options/__init__.py
cornflakes/decorator/click/options/_bg_process.py
cornflakes/decorator/click/options/_config_option.py
cornflakes/decorator/click/options/_global.py
cornflakes/decorator/click/options/_verbose.py
cornflakes/decorator/click/rich/__init__.py
cornflakes/decorator/click/rich/_rich_argument.py
cornflakes/decorator/click/rich/_rich_click.py
cornflakes/decorator/click/rich/_rich_command.py
cornflakes/decorator/click/rich/_rich_config.py
cornflakes-3.3.28.dist-info/LICENSE
cornflakes-3.3.28.dist-info/METADATA
cornflakes-3.3.28.dist-info/WHEEL
cornflakes-3.3.28.dist-info/entry_points.txt
cornflakes-3.3.28.dist-info/RECORD
