Metadata-Version: 2.1
Name: cornflakes
Version: 3.3.28
Summary: Create generic any easy way to manage Configs for your project
Home-page: https://github.com/sgeist/cornflakes
License: Apache2.0
Author: Semjon Geist
Author-email: semjon.geist@ionos.com
Requires-Python: >=3.8,<4.0
Classifier: License :: Other/Proprietary License
Classifier: Programming Language :: Python :: 3
Classifier: Programming Language :: Python :: 3.8
Classifier: Programming Language :: Python :: 3.9
Classifier: Programming Language :: Python :: 3.10
Classifier: Programming Language :: Python :: 3.11
Requires-Dist: PyYAML (>=6.0.1,<7.0.0)
Requires-Dist: click (>=8.1.3,<9.0.0)
Requires-Dist: rich (==13.5.2)
Requires-Dist: rich-rst (>=1.1.7,<2.0.0)
Requires-Dist: toml (>=0.10.2,<0.11.0)
Requires-Dist: typeguard (>=4.1.3,<5.0.0)
Requires-Dist: typing-extensions (>=4.7.1,<5.0.0)
Requires-Dist: validators (>=0.20,<0.23)
Project-URL: Documentation, https://cornflakes.readthedocs.io
Project-URL: Repository, https://github.com/sgeist/cornflakes
